{
  "required": true,
  "package": "corgitaco.betterweather.mixin",
  "compatibilityLevel": "JAVA_8",
  "refmap": "betterweather.refmap.json",
  "mixins": [
    "MixinWorld",
    "access.BiomeAccess",
    "access.RegistryAccess",
    "biome.MixinBiome",
    "block.MixinAbstractBlockstate",
    "client.MixinDebugOverGui",
    "entity.MixinBreedGoal",
    "network.MixinPlayerList",
    "server.MixinCommands",
    "server.MixinMinecraftServer",
    "server.MixinServerWorld",
    "server.MixinWeatherCommand"
  ],
  "client": [
    "client.MixinBiomeClient",
    "client.MixinClientWorld",
    "client.MixinDimensionRenderInfo",
    "client.MixinFogRenderer",
    "client.MixinKeyboardListener",
    "client.MixinLeavesBlock"
  ],
  "injectors": {
    "defaultRequire": 1
  },
  "minVersion": "0.8"
}